numeph/__init__.py
numeph/core.py
numeph/julian.py
numeph/utils.py
numeph-0.3.4.dist-info/LICENSE.txt
numeph-0.3.4.dist-info/METADATA
numeph-0.3.4.dist-info/WHEEL
numeph-0.3.4.dist-info/top_level.txt
numeph-0.3.4.dist-info/RECORD
