Metadata-Version: 2.1
Name: numeph
Version: 0.3.4
Summary: Convert JPL SPK ephemeris to numpy array
Home-page: https://github.com/behrouzz/numeph
Author: Behrouz Safari
Author-email: behrouz.safari@gmail.com
License: MIT
Platform: UNKNOWN
Classifier: Programming Language :: Python :: 3
Classifier: License :: OSI Approved :: MIT License
Classifier: Operating System :: OS Independent
Requires-Python: >=3.4
License-File: LICENSE.txt
Requires-Dist: numpy
Requires-Dist: jplephem
